{
  "main": {
    "id": "ea4e9c84cfdef53e",
    "type": "split",
    "children": [
      {
        "id": "c0dc0a59f6fc5471",
        "type": "tabs",
        "children": [
          {
            "id": "29c9167cd900e910",
            "type": "leaf",
            "state": {
              "type": "markdown",
              "state": {
                "file": "literature/folland1999real.md",
                "mode": "source",
                "backlinks": true,
                "source": false
              }
            }
          },
          {
            "id": "4bfa3a25cdfb5d01",
            "type": "leaf",
            "state": {
              "type": "markdown",
              "state": {
                "file": ".private/synthesis/Democratizing academic research.md",
                "mode": "source",
                "backlinks": true,
                "source": false
              }
            }
          }
        ],
        "currentTab": 1
      }
    ],
    "direction": "vertical"
  },
  "left": {
    "id": "eccbb732bf64175c",
    "type": "split",
    "children": [
      {
        "id": "96bf74aabfefe43e",
        "type": "tabs",
        "children": [
          {
            "id": "1cbd81d064643cf6",
            "type": "leaf",
            "state": {
              "type": "file-explorer",
              "state": {
                "sortOrder": "alphabetical"
              }
            }
          },
          {
            "id": "ae53d3ec9778a3e3",
            "type": "leaf",
            "state": {
              "type": "search",
              "state": {
                "query": "",
                "matchingCase": false,
                "explainSearch": false,
                "collapseAll": false,
                "extraContext": false,
                "sortOrder": "alphabetical"
              }
            }
          },
          {
            "id": "7f7de53e2269880f",
            "type": "leaf",
            "state": {
              "type": "bookmarks",
              "state": {}
            }
          }
        ]
      }
    ],
    "direction": "horizontal",
    "width": 300
  },
  "right": {
    "id": "2c0009862f3d9fb4",
    "type": "split",
    "children": [
      {
        "id": "5c588999c2dadd4c",
        "type": "tabs",
        "children": [
          {
            "id": "3ab6e4753b417c5b",
            "type": "leaf",
            "state": {
              "type": "backlink",
              "state": {
                "file": ".private/synthesis/Democratizing academic research.md",
                "collapseAll": false,
                "extraContext": false,
                "sortOrder": "alphabetical",
                "showSearch": false,
                "searchQuery": "",
                "backlinkCollapsed": false,
                "unlinkedCollapsed": true
              }
            }
          },
          {
            "id": "c5017d37f4351ff4",
            "type": "leaf",
            "state": {
              "type": "outgoing-link",
              "state": {
                "file": ".private/synthesis/Democratizing academic research.md",
                "linksCollapsed": false,
                "unlinkedCollapsed": true
              }
            }
          },
          {
            "id": "13543e387f63ee59",
            "type": "leaf",
            "state": {
              "type": "tag",
              "state": {
                "sortOrder": "frequency",
                "useHierarchy": true
              }
            }
          },
          {
            "id": "fbaf46fd12f7ae83",
            "type": "leaf",
            "state": {
              "type": "outline",
              "state": {
                "file": ".private/synthesis/Democratizing academic research.md"
              }
            }
          }
        ],
        "currentTab": 3
      }
    ],
    "direction": "horizontal",
    "width": 300,
    "collapsed": true
  },
  "left-ribbon": {
    "hiddenItems": {
      "switcher:Open quick switcher": false,
      "graph:Open graph view": false,
      "canvas:Create new canvas": false,
      "daily-notes:Open today's daily note": false,
      "templates:Insert template": false,
      "command-palette:Open command palette": false,
      "zk-prefixer:Create new unique note": false
    }
  },
  "active": "4bfa3a25cdfb5d01",
  "lastOpenFiles": [
    "literature/folland1999real.md",
    ".git/index.lock",
    "literature/folland1999real-Ch0.md",
    "atomic/Bochner's Theorem.md",
    "atomic/BM Decomposition.md",
    "literature/folland1999real-Ch1.md",
    ".private/.git/index.lock",
    ".obsidian/plugins/metadata-extractor/.git/index.lock",
    "literature/README.md",
    "README.md",
    "Pasted image 20231001151958.png",
    "blog/README.md",
    ".private/daily/Untitled.md",
    ".private/daily/using NVIDIA Pytorch docker.md",
    ".private/daily/20230420020123.md",
    ".private/daily/20230418121100.md",
    ".private/daily/20230418110900.md",
    ".private/daily/20230418094500.md",
    ".private/daily/20230417164700.md",
    ".private/daily/20230417163700.md",
    ".private/daily/20221217104400.md",
    ".private/daily/20221201170000.md",
    ".private/daily/20221029131600.md",
    ".private/daily/20220916121600.md",
    ".private/daily/20220716180700.md",
    ".private/daily/20220523161100.md",
    ".private/daily/20220517144900.md",
    ".private/daily/20220511202300.md",
    ".private/daily/20220511153600.md",
    ".private/.git/objects/16/34b492785a27ae737adc330809f69cdc890235",
    ".private/.git/objects/15/e5e18ea4bebd4c0899a0474f46149f46cf0978",
    ".private/.git/AUTO_MERGE",
    ".private/.git/objects/27",
    ".private/.git/objects/27/bca3709755efe303b0a1cf8a7848ecbf83df97",
    ".private/.git/objects/56/0ea3f13aefe7cdbf96437712fe29fdeb9c7b87",
    ".private/.git/rebase-merge/author-script"
  ]
}